gym_tictactoe_np/__init__.py
gym_tictactoe_np/envs/__init__.py
gym_tictactoe_np/envs/tictactoe_np_env.py
gym_tictactoe_np-0.3.0.dist-info/LICENSE.txt
gym_tictactoe_np-0.3.0.dist-info/WHEEL
gym_tictactoe_np-0.3.0.dist-info/METADATA
gym_tictactoe_np-0.3.0.dist-info/RECORD
